aladdin/__init__.py
aladdin/cli.py
aladdin/compiler/constraint_factory.py
aladdin/compiler/feature_factory.py
aladdin/compiler/repo_reader.py
aladdin/compiler/transformation_factory.py
aladdin/data_file.py
aladdin/data_source/__init__.py
aladdin/data_source/batch_data_source.py
aladdin/data_source/stream_data_source.py
aladdin/enricher.py
aladdin/entity_data_source.py
aladdin/exceptions.py
aladdin/feature_source.py
aladdin/feature_store.py
aladdin/feature_view/combined_view.py
aladdin/feature_view/compiled_feature_view.py
aladdin/feature_view/feature_view.py
aladdin/feature_view/feature_view_metadata.py
aladdin/feature_view/tests/test_brest_cancer.py
aladdin/feature_view/tests/test_brest_cancer_event_timestamp.py
aladdin/feature_view/tests/test_brest_cancer_standard_scaling.py
aladdin/feature_view/tests/test_combined_view.py
aladdin/feature_view/tests/test_hidden_variable.py
aladdin/job_factories.py
aladdin/job_factory.py
aladdin/local/__init__.py
aladdin/local/factory.py
aladdin/local/job.py
aladdin/local/source.py
aladdin/model.py
aladdin/online_source.py
aladdin/psql/__init__.py
aladdin/psql/data_source.py
aladdin/psql/factory.py
aladdin/psql/jobs.py
aladdin/redis/__init__.py
aladdin/redis/config.py
aladdin/redis/job.py
aladdin/redis/stream.py
aladdin/redis/tests/test_redis_job.py
aladdin/redshift/__init__.py
aladdin/redshift/data_source.py
aladdin/redshift/factory.py
aladdin/request/retrival_request.py
aladdin/request/tests/test_feature_request_generation.py
aladdin/retrival_job.py
aladdin/s3/__init__.py
aladdin/s3/config.py
aladdin/s3/factory.py
aladdin/s3/storage.py
aladdin/schemas/codable.py
aladdin/schemas/constraints.py
aladdin/schemas/derivied_feature.py
aladdin/schemas/feature.py
aladdin/schemas/repo_definition.py
aladdin/schemas/transformation.py
aladdin/server.py
aladdin/split_strategy.py
aladdin/storage.py
aladdin/tests/test_cache_enricher.py
aladdin/tests/test_statistic_enricher.py
aladdin/tests/test_std_transformation.py
aladdinml-0.0.28a0.dist-info/entry_points.txt
aladdinml-0.0.28a0.dist-info/WHEEL
aladdinml-0.0.28a0.dist-info/METADATA
aladdinml-0.0.28a0.dist-info/RECORD
