Metadata-Version: 2.1
Name: aladdinml
Version: 0.0.28a0
Summary: A scalable feature store that makes it easy to productionise and manage ML and AI projects
Home-page: https://github.com/otovo/aladdin
License: Apache-2.0
Keywords: python,typed,ml,prediction,feature,store,feature-store,feast,tecton
Author: Mats E. Mollestad
Author-email: mats@mollestad.no
Requires-Python: >=3.10,<4.0
Classifier: Development Status :: 3 - Alpha
Classifier: Environment :: Web Environment
Classifier: Intended Audience :: Developers
Classifier: License :: OSI Approved :: Apache Software License
Classifier: Operating System :: OS Independent
Classifier: Programming Language :: Python
Classifier: Programming Language :: Python :: 3
Classifier: Programming Language :: Python :: 3.10
Classifier: Programming Language :: Python :: 3.11
Classifier: Programming Language :: Python :: 3.10
Classifier: Topic :: Internet :: WWW/HTTP
Classifier: Topic :: Internet :: WWW/HTTP :: Dynamic Content
Classifier: Topic :: Scientific/Engineering :: Artificial Intelligence
Classifier: Topic :: Software Development
Classifier: Topic :: Software Development :: Libraries
Classifier: Topic :: Software Development :: Libraries :: Application Frameworks
Classifier: Topic :: Software Development :: Libraries :: Python Modules
Provides-Extra: aws
Provides-Extra: dask
Provides-Extra: pandera
Provides-Extra: psql
Provides-Extra: redis
Provides-Extra: server
Requires-Dist: Jinja2 (>=3.1.2,<4.0.0)
Requires-Dist: aioaws (>=0.12,<0.13); extra == "aws"
Requires-Dist: asgi-correlation-id (>=3.0.0,<4.0.0); extra == "server"
Requires-Dist: asyncpg (>=0.25.0,<0.26.0); extra == "psql"
Requires-Dist: click (>=8.1.3,<9.0.0)
Requires-Dist: dask[dataframe] (>=2022.7.0,<2023.0.0); extra == "dask"
Requires-Dist: databases (>=0.5.5,<0.6.0); extra == "aws" or extra == "psql"
Requires-Dist: dill (>=0.3.4,<0.4.0)
Requires-Dist: fastapi (>=0.77.1,<0.78.0); extra == "server"
Requires-Dist: mashumaro (>=3.0.1,<4.0.0)
Requires-Dist: nest-asyncio (>=1.5.5,<2.0.0)
Requires-Dist: pandas (>=1.3.1,<2.0.0)
Requires-Dist: pandera (>=0.13.3,<0.14.0); extra == "pandera"
Requires-Dist: pyarrow (>=8.0.0,<9.0.0)
Requires-Dist: redis (>=4.3.1,<5.0.0); extra == "redis"
Requires-Dist: uvicorn (>=0.17.6,<0.18.0); extra == "server"
Project-URL: Repository, https://github.com/otovo/aladdin
